python_imagesearch/__init__.py
python_imagesearch/imagesearch.py
python_imageseach_drov0-1.1.2.dist-info/LICENSE
python_imageseach_drov0-1.1.2.dist-info/METADATA
python_imageseach_drov0-1.1.2.dist-info/WHEEL
python_imageseach_drov0-1.1.2.dist-info/top_level.txt
python_imageseach_drov0-1.1.2.dist-info/RECORD
